<bill session="103" type="h" number="992" updated="2010-04-19T01:41:59-04:00">
	<state datetime="1993-02-18">REFERRED</state>
	<status><introduced datetime="1993-02-18"/></status>

	<introduced datetime="1993-02-18"/>
	<titles>
		<title type="official" as="introduced">To provide that individuals who exhaust their rights to disaster unemployment benefits shall be entitled to emergency unemployment benefits.</title>
	</titles>
	<sponsor id="400554"/>
	<cosponsors>

	</cosponsors>
	<actions>
		<action datetime="1993-02-18"><text>Sponsor introductory remarks on measure. (CR H698-699)</text></action>
		<action datetime="1993-02-18"><text>Referred to the House Committee on Ways and Means.</text></action>
		<action datetime="1993-02-23"><committee name="House Committee on Ways and Means"/><text>Referred to the Subcommittee on Human Resources.</text></action>
	</actions>
	<committees>
		<committee code="HSWM" name="House Ways and Means" activity="Referral, In Committee" />
		<committee code="HSWM-03" name="House Ways and Means" subcommittee="Human Resources" activity="Referral" />
	</committees>
	<relatedbills>

	</relatedbills>
	<subjects>
		<term name="Unemployment insurance"/>
		<term name="Disaster relief"/>
	</subjects>
	<amendments>

	</amendments>
	<summary>
	2/18/1993--Introduced.
Amends the Emergency Unemployment Compensation Act of 1991 to entitle to emergency unemployment benefits, under specified conditions, individuals who exhaust their rights to disaster unemployment benefits under the Robert T. Stafford Disaster Relief and Emergency Assistance Act.

	</summary>
</bill>
