<bill session="103" type="hc" number="128" updated="2010-04-18T21:20:51-04:00">
	<state datetime="1993-07-29">REFERRED</state>
	<status><introduced datetime="1993-07-29"/></status>

	<introduced datetime="1993-07-29"/>
	<titles>
		<title type="official" as="introduced">Commending Israel concerning the decision of the Supreme Court of Israel in the case of John Demjanjuk, Sr.</title>
	</titles>
	<sponsor id="400611"/>
	<cosponsors>

	</cosponsors>
	<actions>
		<action datetime="1993-07-29"><text>Sponsor introductory remarks on measure. (CR H5455-5456)</text></action>
		<action datetime="1993-07-29"><text>Referred to the House Committee on Foreign Affairs.</text></action>
		<action datetime="1993-08-10"><committee name="House Committee on Foreign Affairs"/><text>Referred to the Subcommittee on Europe and the Middle East.</text></action>
	</actions>
	<committees>
		<committee code="HSFA" name="House Foreign Affairs" activity="Referral, In Committee" />
		<committee code="" name="House Foreign Affairs" subcommittee="Europe and the Middle East" activity="Referral" />
	</committees>
	<relatedbills>

	</relatedbills>
	<subjects>
		<term name="Foreign relations"/>
		<term name="Capital punishment"/>
		<term name="Commemorations"/>
		<term name="Concentration camps"/>
		<term name="Congressional tributes"/>
		<term name="Courts"/>
		<term name="Israel"/>
		<term name="Jewish holocaust (1939-1945)"/>
		<term name="National socialism"/>
		<term name="Sentences (Criminal procedure)"/>
		<term name="War crime trials"/>
	</subjects>
	<amendments>

	</amendments>
	<summary>
	7/29/1993--Introduced.
Commends the decision by the Israeli Supreme Court to overturn the conviction and death sentence in the case of John Demjanjuk, Sr.

	</summary>
</bill>
