<bill session="103" type="hc" number="226" updated="2010-04-18T21:36:17-04:00">
	<state datetime="1994-03-17">REFERRED</state>
	<status><introduced datetime="1994-03-17"/></status>

	<introduced datetime="1994-03-17"/>
	<titles>
		<title type="official" as="introduced">Expressing the sense of Congress that any welfare reform legislation which requires recipients of aid to families with dependent children to find employment within a certain time as a condition of receiving benefits should exempt recipients who collect benefits from a State with an unemployment rate that is at least 110 percent of the national average unemployment rate.</title>
	</titles>
	<sponsor id="407044"/>
	<cosponsors>

	</cosponsors>
	<actions>
		<action datetime="1994-03-17"><text>Referred to the House Committee on Ways and Means.</text></action>
		<action datetime="1994-03-21"><committee name="House Committee on Ways and Means"/><text>Referred to the Subcommittee on Human Resources.</text></action>
	</actions>
	<committees>
		<committee code="HSWM" name="House Ways and Means" activity="Referral, In Committee" />
		<committee code="HSWM-03" name="House Ways and Means" subcommittee="Human Resources" activity="Referral" />
	</committees>
	<relatedbills>

	</relatedbills>
	<subjects>
		<term name="Social security"/>
		<term name="Aid to dependent children"/>
		<term name="Children"/>
		<term name="Congress"/>
		<term name="Labor"/>
		<term name="Legislation"/>
		<term name="Public assistance programs"/>
		<term name="Social security eligibility"/>
		<term name="Unemployed"/>
		<term name="Unemployment"/>
		<term name="Welfare"/>
	</subjects>
	<amendments>

	</amendments>
	<summary>
	3/17/1994--Introduced.
Expresses the sense of the Congress that any welfare reform legislation which requires recipients of Aid to Families With Dependent Children (AFDC) to find employment within a certain time as a condition of receiving benefits should exempt recipients who collect benefits from a State with an unemployment rate that is at least 110 percent of the national average unemployment rate.

	</summary>
</bill>
