<bill session="103" type="hj" number="158" updated="2010-04-18T22:15:54-04:00">
	<state datetime="1993-03-17">REFERRED</state>
	<status><introduced datetime="1993-03-17"/></status>

	<introduced datetime="1993-03-17"/>
	<titles>
		<title type="official" as="introduced">Proposing an amendment to the Constitution of the United States with respect to the right to life.</title>
	</titles>
	<sponsor id="403545"/>
	<cosponsors>
		<cosponsor id="400380" joined="1993-03-17"/>
		<cosponsor id="400191" joined="1993-11-17"/>
		<cosponsor id="406863" joined="1993-06-14"/>
		<cosponsor id="400192" joined="1993-03-17"/>
		<cosponsor id="400055" joined="1993-03-17"/>
		<cosponsor id="400551" joined="1993-05-24"/>
		<cosponsor id="411178" joined="1993-03-17"/>
		<cosponsor id="405033" joined="1993-03-17"/>
	</cosponsors>
	<actions>
		<action datetime="1993-03-17"><text>Referred to the House Committee on Judiciary.</text></action>
		<action datetime="1993-03-18"><text>Sponsor introductory remarks on measure. (CR E685-686)</text></action>
		<action datetime="1993-03-22"><committee name="House Committee on Judiciary"/><text>Referred to the Subcommittee on Civil and Constitutional Rights.</text></action>
	</actions>
	<committees>
		<committee code="HSJU" name="House Judiciary" activity="Referral, In Committee" />
		<committee code="" name="House Judiciary" subcommittee="Civil and Constitutional Rights" activity="Referral" />
	</committees>
	<relatedbills>

	</relatedbills>
	<subjects>
		<term name="Abortion"/>
		<term name="Constitutional amendments"/>
		<term name="State laws"/>
	</subjects>
	<amendments>

	</amendments>
	<summary>
	3/17/1993--Introduced.
Constitutional Amendment - Defines &quot;person&quot; to include the unborn for the purpose of the right to life guarantee the fifth and fourteenth amendments. Prohibits any unborn person from being deprived of life by any person. States that nothing in this Act shall prohibit a law allowing justification to be shown for only those medical procedures required to prevent the death of the pregnant woman or her unborn offspring, as long as such law requires every reasonable effort to preserve the life of each.

	</summary>
</bill>
