<bill session="103" type="s" number="1153" updated="2012-07-17T06:18:57-04:00">
	<state datetime="1993-06-24">REFERRED</state>
	<status><introduced datetime="1993-06-24"/></status>

	<introduced datetime="1993-06-24"/>
	<titles>
		<title type="official" as="introduced">A bill to suspend temporarily the duty on Tacrolimus in bulk or measured dose form subject to approval by the Food and Drug Administration.</title>
	</titles>
	<sponsor id="409917"/>
	<cosponsors>

	</cosponsors>
	<actions>
		<action datetime="1993-06-24" state="REFERRED"><text>Read twice and referred to the Committee on Finance.</text></action>
	</actions>
	<committees>
		<committee code="SSFI" name="Senate Finance" activity="Referral, In Committee" />
	</committees>
	<relatedbills>
		<bill relation="identical" session="103" type="h" number="2279" />
	</relatedbills>
	<subjects>
		<term name="Foreign trade and international finance"/>
		<term name="Chemicals"/>
		<term name="Drugs"/>
		<term name="Tariff"/>
	</subjects>
	<amendments>

	</amendments>
	<summary>
	6/24/1993--Introduced.
Amends the Harmonized Tariff Schedule of the United States to suspend, through December 31, 1994, the duty on tacrolimus in measured dose and bulk form.

	</summary>
</bill>
