<bill session="103" type="sr" number="61" updated="2010-04-19T22:08:58-04:00">
	<state datetime="1993-02-03">REFERRED</state>
	<status><introduced datetime="1993-02-03"/></status>

	<introduced datetime="1993-02-03"/>
	<titles>
		<title type="official" as="introduced">A resolution amending the Standing Rules of the Senate.</title>
	</titles>
	<sponsor id="400565"/>
	<cosponsors>

	</cosponsors>
	<actions>
		<action datetime="1993-02-03"><text>Sponsor introductory remarks on measure. (CR S1201-1202)</text></action>
		<action datetime="1993-02-03"><text>Referred to the Committee on Rules.</text></action>
	</actions>
	<committees>
		<committee code="SSRA" name="Senate Rules and Administration" activity="Referral, In Committee" />
	</committees>
	<relatedbills>

	</relatedbills>
	<subjects>
		<term name="Senate"/>
		<term name="Congressional committees (Senate)"/>
		<term name="Congressional ethics"/>
		<term name="Ex-Members of Congress"/>
		<term name="Judges"/>
		<term name="Members of Congress (Senate)"/>
	</subjects>
	<amendments>

	</amendments>
	<summary>
	2/3/1993--Introduced.
Amends Senate Resolution 338, 88th Congress, to change the membership of the Select Committee on Ethics from Members of the Senate to three private citizens. Requires two of such citizens to be former Members of the Congress (preferably Senators) and one to be a retired Federal judge.

	</summary>
</bill>
